graphql_example/__init__.py
graphql_example/cli.py
graphql_example/db_queries.py
graphql_example/factories.py
graphql_example/graphql_example.py
graphql_example/log.json
graphql_example/logging_utilities.py
graphql_example/model.py
graphql_example/on_cleanup.py
graphql_example/on_startup.py
graphql_example-0.4.4.dist-info/DESCRIPTION.rst
graphql_example-0.4.4.dist-info/METADATA
graphql_example-0.4.4.dist-info/RECORD
graphql_example-0.4.4.dist-info/WHEEL
graphql_example-0.4.4.dist-info/entry_points.txt
graphql_example-0.4.4.dist-info/metadata.json
graphql_example-0.4.4.dist-info/top_level.txt
tests/__init__.py
tests/test_graphql_example.py
