Metadata-Version: 2.0
Name: graphql-example
Version: 0.4.4
Summary: A simple graphql server
Home-page: https://github.com/kalohq/graphql-example
Author: Stephan Fitzpatrick
Author-email: knowsuchagency@gmail.com
License: Apache 2.0 license
Keywords: graphql-example
Platform: UNKNOWN
Classifier: Development Status :: 2 - Pre-Alpha
Classifier: License :: OSI Approved :: Apache Software License
Classifier: Natural Language :: English
Classifier: Programming Language :: Python :: 3.6
Requires-Dist: attrs
Requires-Dist: click
Requires-Dist: eliot
Requires-Dist: eliot-tree
Requires-Dist: aiohttp
Requires-Dist: graphene
Requires-Dist: aiohttp-mako
Requires-Dist: mimesis
Requires-Dist: aiohttp-graphql
Requires-Dist: markdown
Provides-Extra: dev
Requires-Dist: bumpversion; extra == 'dev'
Requires-Dist: coverage; extra == 'dev'
Requires-Dist: cryptography; extra == 'dev'
Requires-Dist: flake8; extra == 'dev'
Requires-Dist: pytest-runner; extra == 'dev'
Requires-Dist: pyyaml; extra == 'dev'
Requires-Dist: tox; extra == 'dev'
Requires-Dist: wheel; extra == 'dev'
Requires-Dist: fabric3; extra == 'dev'
Requires-Dist: readme; extra == 'dev'
Requires-Dist: twine; extra == 'dev'
Requires-Dist: yapf; extra == 'dev'
Requires-Dist: pytest; extra == 'dev'
Requires-Dist: pytest-aiohttp; extra == 'dev'
Requires-Dist: jupyter; extra == 'dev'
Requires-Dist: jupyter-contrib-nbextensions; extra == 'dev'
Requires-Dist: markdown; extra == 'dev'
Provides-Extra: development
Requires-Dist: bumpversion; extra == 'development'
Requires-Dist: coverage; extra == 'development'
Requires-Dist: cryptography; extra == 'development'
Requires-Dist: flake8; extra == 'development'
Requires-Dist: pytest-runner; extra == 'development'
Requires-Dist: pyyaml; extra == 'development'
Requires-Dist: tox; extra == 'development'
Requires-Dist: wheel; extra == 'development'
Requires-Dist: fabric3; extra == 'development'
Requires-Dist: readme; extra == 'development'
Requires-Dist: twine; extra == 'development'
Requires-Dist: yapf; extra == 'development'
Requires-Dist: pytest; extra == 'development'
Requires-Dist: pytest-aiohttp; extra == 'development'
Requires-Dist: jupyter; extra == 'development'
Requires-Dist: jupyter-contrib-nbextensions; extra == 'development'
Requires-Dist: markdown; extra == 'development'
Provides-Extra: test
Requires-Dist: bumpversion; extra == 'test'
Requires-Dist: coverage; extra == 'test'
Requires-Dist: cryptography; extra == 'test'
Requires-Dist: flake8; extra == 'test'
Requires-Dist: pytest-runner; extra == 'test'
Requires-Dist: pyyaml; extra == 'test'
Requires-Dist: tox; extra == 'test'
Requires-Dist: wheel; extra == 'test'
Requires-Dist: fabric3; extra == 'test'
Requires-Dist: readme; extra == 'test'
Requires-Dist: twine; extra == 'test'
Requires-Dist: yapf; extra == 'test'
Requires-Dist: pytest; extra == 'test'
Requires-Dist: pytest-aiohttp; extra == 'test'
Requires-Dist: jupyter; extra == 'test'
Requires-Dist: jupyter-contrib-nbextensions; extra == 'test'
Requires-Dist: markdown; extra == 'test'
Provides-Extra: testing
Requires-Dist: bumpversion; extra == 'testing'
Requires-Dist: coverage; extra == 'testing'
Requires-Dist: cryptography; extra == 'testing'
Requires-Dist: flake8; extra == 'testing'
Requires-Dist: pytest-runner; extra == 'testing'
Requires-Dist: pyyaml; extra == 'testing'
Requires-Dist: tox; extra == 'testing'
Requires-Dist: wheel; extra == 'testing'
Requires-Dist: fabric3; extra == 'testing'
Requires-Dist: readme; extra == 'testing'
Requires-Dist: twine; extra == 'testing'
Requires-Dist: yapf; extra == 'testing'
Requires-Dist: pytest; extra == 'testing'
Requires-Dist: pytest-aiohttp; extra == 'testing'
Requires-Dist: jupyter; extra == 'testing'
Requires-Dist: jupyter-contrib-nbextensions; extra == 'testing'
Requires-Dist: markdown; extra == 'testing'
